Metadata-Version: 2.1
Name: nanograd-aman
Version: 0.1.0
Summary: A lightweight backpropagation package for neural networks
Home-page: https://github.com/NeuralNoble/nanograd
Author: Aman Anand
Author-email: coursesxyz403@gmail.com
Classifier: Programming Language :: Python :: 3
Classifier: License :: OSI Approved :: MIT License
Classifier: Operating System :: OS Independent
Requires-Python: >=3.6
Requires-Dist: numpy
Requires-Dist: graphviz
